confusion/__init__.py
confusion/config.py
confusion/parser.py
confusion/test/__init__.py
confusion/test/test_cfn2dot.py
confusion/test/test_config.py
confusion/test/test_parser.py
confusion/utils/__init__.py
confusion/utils/cfn2dot.py
confusion-0.4.0.dist-info/LICENSE
confusion-0.4.0.dist-info/METADATA
confusion-0.4.0.dist-info/WHEEL
confusion-0.4.0.dist-info/top_level.txt
confusion-0.4.0.dist-info/RECORD
