Metadata-Version: 2.1
Name: confusion
Version: 0.4.0
Summary: A pre-processor for TOML files.
Author-email: Tundish <tundish@gigeconomy.org.uk>
Maintainer-email: Tundish <tundish@gigeconomy.org.uk>
License: GNU LESSER GENERAL PUBLIC LICENSE
Keywords: configparser,ini,TOML,cfn
Classifier: Development Status :: 4 - Beta
Classifier: Programming Language :: Python
Requires-Python: >=3.8
License-File: LICENSE
Requires-Dist: tomli (>=2.0.0) ; python_version < "3.11"
